<PropertySet name="default-component-InterestPoint-InteractSwitch001" nameUID="0x78F2F4B" schema="default-component-InterestPoint-InteractSwitch001">
    <Property name="BehaviourFile" type="String">Data\Global\Act\POI\POI_InteractSwitch001.act</Property>
    <Property name="Category" type="Symbol" Symbol="0x9548F73B">Mission</Property>
    <Property name="Description" type="Symbol" Symbol="0x91E6FE47">Interaction Switch 001 POI</Property>
    <Property name="HasBehaviour" type="Boolean">True</Property>
    <Property name="component_InterestPoint" type="PropSet">
        <PropertySet>
            <Parent>default-component-InterestPoint</Parent>
        </PropertySet>
    </Property>
    <Property name="schema_classlist" type="PropSet"/>
</PropertySet>
