<PropertySet name="object-physical-prop-LOB_AnswerMachine001" nameUID="0x53F2AAF9" schema="object-physical-prop-LOB_AnswerMachine001">
    <Parent>object-physical-prop-VisibleProp</Parent>
    <Property name="Description" type="String">LOB_AnswerMachine001</Property>
    <Property name="RadarHighlightType" type="Symbol" Symbol="0x299760D">Interactable</Property>
    <Property name="component_BaseAnimation" type="PropSet">
        <BinData>
            <DestroyAttachedCharacters type="Boolean">true</DestroyAttachedCharacters>
            <RigName type="String">LOB_AnswerMachine001</RigName>
            <PoseDriverSet type="Symbol"/>
            <PoseDriverSetHD type="Symbol"/>
            <RequiredAnimBanks type="List"/>
        </BinData>
    </Property>
    <Property name="component_CharacterAnimation" type="PropSet">
        <BinData>
            <DestroyAttachedCharacters type="Boolean">true</DestroyAttachedCharacters>
            <RigName type="String">LOB_AnswerMachine001</RigName>
            <PoseDriverSet type="Symbol"/>
            <PoseDriverSetHD type="Symbol"/>
            <RequiredAnimBanks type="List"/>
        </BinData>
    </Property>
</PropertySet>
