<PropertySet name="object-physical-vehicle-TransTerrReward02" nameUID="0xD5ECAA7B" schema="object-physical-vehicle-TransTerrReward02">
    <Parent>object-physical-vehicle-TransTerr05</Parent>
    <Property name="VehicleLook" type="List">
        <Property type="String">WhiteNewPaint</Property>
    </Property>
    <Property name="component_StreamedResource" type="PropSet">
        <BinData>
            <ResourceTags type="List"/>
            <ResourceList type="List">
                <Property type="Symbol" Symbol="0x1FAEF61A">Data\Vehicles_New\TransTerr01</Property>
                <Property type="Symbol" Symbol="0x3CA0ACF">Data\Vehicles_New\WheelStyle40</Property>
                <Property type="Symbol" Symbol="0x2E6AA72D">Data\Vehicles_New\WheelStyle40_Rear</Property>
                <Property type="Symbol" Symbol="0xF40FF82A">Data\Vehicles_New\TransTerr01_Var01</Property>
                <Property type="Symbol" Symbol="0xF94CDEF3">Data\Vehicles_New\TransTerr01_Var02</Property>
            </ResourceList>
            <ComponentList type="List"/>
            <TextureSetList type="List">
                <Property type="Symbol" Symbol="0x56A76DF2">Data\Vehicles_New\TransTerr01_ts002</Property>
                <Property type="Symbol" Symbol="0xD4912A4E">Data\Vehicles_New\WheelStyle40_ts_002</Property>
                <Property type="Symbol"/>
                <Property type="Symbol"/>
                <Property type="Symbol"/>
            </TextureSetList>
            <EntityType type="Symbol">TransTerr</EntityType>
            <TrueCrowdSelectionType type="UInt32">2</TrueCrowdSelectionType>
            <BMIMin type="Float32">0</BMIMin>
            <BMIMax type="Float32">0</BMIMax>
            <PartList type="List"/>
        </BinData>
    </Property>
</PropertySet>
