<PropertySet name="object-physical-character-ValetCNY" nameUID="0x95E72CEE" schema="object-physical-character-ValetCNY">
    <Parent>object-physical-character-Thug_Wsg_brawler</Parent>
    <Property name="Description" type="String">Wei's Valet in CNY:  - Valet</Property>
    <Property name="ForceNoHelmet" type="Boolean">True</Property>
    <Property name="component_CharacterProperties" type="PropSet">
        <PropertySet>
            <Parent>eFIGHTING_CLASS_NON_COMBATANT</Parent>
        </PropertySet>
        <BinData>
            <simObjectType type="Symbol">eSIM_OBJ_TYPE_CHARACTER</simObjectType>
            <subTargetingProfile type="Symbol">Targeting-SubTargetingProfiles-Character</subTargetingProfile>
            <simObjectCharacterType type="Symbol">eCHARACTER_TYPE_THUG</simObjectCharacterType>
            <simObjectCharacterIsFemale type="Boolean">false</simObjectCharacterIsFemale>
            <simObjectCharacterFightingClass type="Symbol">eFIGHTING_CLASS_NON_COMBATANT</simObjectCharacterFightingClass>
            <Stamina type="Int32">100</Stamina>
            <PoiCooldownTimeMin type="Float32">0</PoiCooldownTimeMin>
            <PoiCooldownTimeMax type="Float32">0</PoiCooldownTimeMax>
            <FactionClass type="Symbol">ALLIED_SPECIAL_1</FactionClass>
            <Gender type="Symbol">Male</Gender>
            <IsTired type="Boolean">false</IsTired>
        </BinData>
    </Property>
    <Property name="component_SimObjectProperties" type="PropSet">
        <PropertySet>
            <Parent>eFIGHTING_CLASS_NON_COMBATANT</Parent>
        </PropertySet>
        <BinData>
            <simObjectType type="Symbol">eSIM_OBJ_TYPE_CHARACTER</simObjectType>
            <subTargetingProfile type="Symbol">Targeting-SubTargetingProfiles-Character</subTargetingProfile>
        </BinData>
    </Property>
    <Property name="component_StreamedResource" type="PropSet">
        <BinData>
            <ResourceTags type="List">
                <Property type="Symbol" Symbol="0x166A8B5C">Male</Property>
                <Property type="Symbol" Symbol="0xC5BA1292">Asian</Property>
                <Property type="Symbol" Symbol="0xB7B39865">Police</Property>
                <Property type="Symbol" Symbol="0xFC4DCAB4">Youth</Property>
            </ResourceTags>
            <ResourceList type="List">
                <Property type="Symbol" Symbol="0x33210B02">Data\Characters_New\AM_H_039</Property>
                <Property type="Symbol" Symbol="0xB70C3E76">Data\Characters_New\AS_B_PoliceOfficer</Property>
            </ResourceList>
            <ComponentList type="List"/>
            <TextureSetList type="List"/>
            <EntityType type="Symbol">TwoPartPed</EntityType>
            <TrueCrowdSelectionType type="UInt32">2</TrueCrowdSelectionType>
            <BMIMin type="Float32">-0.2</BMIMin>
            <BMIMax type="Float32">-0.3</BMIMax>
            <PartList type="List"/>
        </BinData>
    </Property>
</PropertySet>
