<PropertySetResource name="object-physical-character-Conroy_tutorial" nameUID="0x38CA7EFC">
	<!-- Parents -->
	<Parent nameUID="0xCDDBAF9A">object-physical-character-animbanks-ThugQuickStriker</Parent>
	<Parent nameUID="0xC8647A36">object-physical-character-stats-waterstreet_quick</Parent>
	<Parent nameUID="0x7D6166F3">object-physical-character-Conroy</Parent>
	<!-- Properties -->
	<Property name="Grapple" type="Int32">100</Property>
	<Property name="component_AIActionTree" type="PropSet">
		<PropertySet name="component_AIActionTree" nameUID="0x523487F" schema="default-component-AIActionTree">
			<!-- Schema Properties -->
			<Property name="AIBehaviour" type="String">Thug_Behaviour.act</Property>
		</PropertySet>
	</Property>
	<Property name="BlockChance" type="Int32">100</Property>
	<Property name="component_HitReaction" type="PropSet">
		<PropertySet name="component_HitReaction" nameUID="0x1575D886" schema="default-component-HitReaction">
			<!-- Schema Properties -->
			<Property name="HitActFilename" type="String">Data/Global/Act/HitTree.act</Property>
			<Property name="HitReactionOpeningBranchFullPath" type="String"/>
			<Property name="HitReceiverDamageMultiplierPct" type="UInt32">100</Property>
		</PropertySet>
	</Property>
	<Property name="schema_classlist" type="PropSet">
		<PropertySet name="schema_classlist" nameUID="0x17B9254E" schema="default-schema-classlist">
			<!-- Schema Properties -->
			<Property name="ClassTypeIsAllowable" type="Boolean">true</Property>
			<Property name="ClassTypeList" type="List">
				<!-- Elements -->
				<ListProperty type="Symbol" symUID="0xDC76B4F1">Triad</ListProperty>
			</Property>
		</PropertySet>
	</Property>
	<Property name="component_CharacterAnimation" type="PropSet">
		<PropertySet name="component_CharacterAnimation" nameUID="0x34DB99FB" schema="default-component-CharacterAnimation">
			<!-- Schema Parent: component_BaseAnimation -->
		</PropertySet>
	</Property>
	<Property name="HeavyAttackChance" type="Int32">100</Property>
	<Property name="component_BaseAnimation" type="PropSet">
		<PropertySet name="component_CharacterAnimation" nameUID="0x34DB99FB" schema="default-component-CharacterAnimation">
			<!-- Schema Properties -->
			<Property name="DestroyAttachedCharacters" type="Boolean">true</Property>
			<Property name="RigName" type="String">PrimaryBasicMale</Property>
			<Property name="WeightSetFileName" type="String">Data\Global\Act\ChanWeightSets.wst</Property>
			<Property name="PoseDriverSet" type="SymbolUC" symUID="0xE3A9334A">PlayerPed</Property>
			<Property name="RigNameHD" type="String">Conroy_HD</Property>
			<Property name="WeightSetFileNameHD" type="String">Data\Global\Act\NIS_WeightSets.wst</Property>
			<Property name="PoseDriverSetHD" type="SymbolUC"/>
			<Property name="RequiredAnimBanks" type="List">
				<!-- Elements -->
				<ListProperty type="SymbolUC" symUID="0x9F35E28">Thug</ListProperty>
				<ListProperty type="SymbolUC" symUID="0xBCEB5E67">THUG_STRIKES</ListProperty>
				<ListProperty type="SymbolUC" symUID="0xEB4FEEB5">Thug_LowHealth</ListProperty>
				<ListProperty type="SymbolUC" symUID="0xC4F522A7">Thug_QuickStriker</ListProperty>
				<ListProperty type="SymbolUC" symUID="0x35AA897E">Thug_QuickStriker_Strikes</ListProperty>
			</Property>
			<Property name="pad_BaseAnimation" type="UInt32">0</Property>
		</PropertySet>
	</Property>
	<Property name="component_FormationManager" type="PropSet">
		<PropertySet name="component_FormationManager" nameUID="0x8259C690" schema="default-component-FormationManager">
			<!-- Schema Properties -->
			<Property name="NumRanges" type="Int32">4</Property>
			<Property name="NumSlotsInRange0" type="Int32">1</Property>
			<Property name="NumSlotsInRange1" type="Int32">3</Property>
			<Property name="NumSlotsInRange2" type="Int32">4</Property>
			<Property name="NumSlotsInRange3" type="Int32">8</Property>
			<Property name="NormalMaxDistance0" type="Float32">2.9</Property>
			<Property name="NormalMaxDistance1" type="Float32">3.7</Property>
			<Property name="NormalMaxDistance2" type="Float32">5.7</Property>
			<Property name="NormalMaxDistance3" type="Float32">15</Property>
			<Property name="NormalMinTimeBeforeCheckPlayersTarget" type="Float32">0.25</Property>
			<Property name="NormalMaxTimeBeforeCheckPlayersTarget" type="Float32">1</Property>
			<Property name="NormalMinTimeBeforeSwitchFromRange0" type="Float32">99999</Property>
			<Property name="NormalMaxTimeBeforeSwitchFromRange0" type="Float32">999999</Property>
			<Property name="NormalMinTimeBeforeSwitchFromRange1" type="Float32">99999</Property>
			<Property name="NormalMaxTimeBeforeSwitchFromRange1" type="Float32">999999</Property>
			<Property name="NormalMinTimeBeforeSwitchFromRange2" type="Float32">99999</Property>
			<Property name="NormalMaxTimeBeforeSwitchFromRange2" type="Float32">999999</Property>
			<Property name="MobMaxDistance0" type="Float32">2</Property>
			<Property name="MobMaxDistance1" type="Float32">2</Property>
			<Property name="MobMaxDistance2" type="Float32">10.5</Property>
			<Property name="MobMaxDistance3" type="Float32">15</Property>
			<Property name="MobMinTimeBeforeCheckPlayersTarget" type="Float32">0.1</Property>
			<Property name="MobMaxTimeBeforeCheckPlayersTarget" type="Float32">0.1</Property>
			<Property name="MobMinTimeBeforeSwitchFromRange0" type="Float32">5</Property>
			<Property name="MobMaxTimeBeforeSwitchFromRange0" type="Float32">8</Property>
			<Property name="MobMinTimeBeforeSwitchFromRange1" type="Float32">99999</Property>
			<Property name="MobMaxTimeBeforeSwitchFromRange1" type="Float32">999999</Property>
			<Property name="MobMinTimeBeforeSwitchFromRange2" type="Float32">99999</Property>
			<Property name="MobMaxTimeBeforeSwitchFromRange2" type="Float32">999999</Property>
			<Property name="MaxRadialDistanceFromDesiredPosition0" type="Float32">0.25</Property>
			<Property name="MaxRadialDistanceFromDesiredPositionHysteresis0" type="Float32">0.3</Property>
			<Property name="MaxRadialDistanceFromDesiredPositionHysteresisLarge0" type="Float32">0.3</Property>
			<Property name="MaxLateralDistanceFromDesiredPosition0" type="Float32">0.7</Property>
			<Property name="MaxLateralDistanceFromDesiredPositionHysteresis0" type="Float32">1.2</Property>
			<Property name="MaxRadialDistanceFromDesiredPosition1" type="Float32">0.3</Property>
			<Property name="MaxRadialDistanceFromDesiredPositionHysteresis1" type="Float32">0.3</Property>
			<Property name="MaxRadialDistanceFromDesiredPositionHysteresisLarge1" type="Float32">0.3</Property>
			<Property name="MaxLateralDistanceFromDesiredPosition1" type="Float32">1.2</Property>
			<Property name="MaxLateralDistanceFromDesiredPositionHysteresis1" type="Float32">1</Property>
			<Property name="MaxRadialDistanceFromDesiredPosition2" type="Float32">0.5</Property>
			<Property name="MaxRadialDistanceFromDesiredPositionHysteresis2" type="Float32">3</Property>
			<Property name="MaxRadialDistanceFromDesiredPositionHysteresisLarge2" type="Float32">10</Property>
			<Property name="MaxLateralDistanceFromDesiredPosition2" type="Float32">0.5</Property>
			<Property name="MaxLateralDistanceFromDesiredPositionHysteresis2" type="Float32">10</Property>
			<Property name="MaxRadialDistanceFromDesiredPosition3" type="Float32">0.5</Property>
			<Property name="MaxRadialDistanceFromDesiredPositionHysteresis3" type="Float32">6</Property>
			<Property name="MaxRadialDistanceFromDesiredPositionHysteresisLarge3" type="Float32">10</Property>
			<Property name="MaxLateralDistanceFromDesiredPosition3" type="Float32">0.5</Property>
			<Property name="MaxLateralDistanceFromDesiredPositionHysteresis3" type="Float32">10</Property>
			<Property name="MaxRadialDistanceFromDesiredPositionToBeginSprintingWhenTargetSprinting" type="Float32">1</Property>
			<Property name="FacingTypeEnumString" type="String">eFORMATION_FACING_CENTRE</Property>
			<Property name="MaxFacingDifference0" type="Float32">50</Property>
			<Property name="MaxFacingDifferenceHysteresis0" type="Float32">25</Property>
			<Property name="MaxFacingDifference1" type="Float32">50</Property>
			<Property name="MaxFacingDifferenceHysteresis1" type="Float32">25</Property>
			<Property name="MaxFacingDifference2" type="Float32">50</Property>
			<Property name="MaxFacingDifferenceHysteresis2" type="Float32">40</Property>
			<Property name="MaxFacingDifference3" type="Float32">50</Property>
			<Property name="MaxFacingDifferenceHysteresis3" type="Float32">40</Property>
			<Property name="RadialHysteresisModifierMin0" type="Float32">0</Property>
			<Property name="RadialHysteresisModifierMax0" type="Float32">0</Property>
			<Property name="RadialHysteresisModifierMin1" type="Float32">-1</Property>
			<Property name="RadialHysteresisModifierMax1" type="Float32">1</Property>
			<Property name="RadialHysteresisModifierMin2" type="Float32">-2</Property>
			<Property name="RadialHysteresisModifierMax2" type="Float32">2</Property>
			<Property name="RadialHysteresisModifierMin3" type="Float32">-2</Property>
			<Property name="RadialHysteresisModifierMax3" type="Float32">2</Property>
		</PropertySet>
	</Property>
	<Property name="CounterAttack" type="Int32">0</Property>
	<Property name="object_physical_character_stats_BaseAttackParameters" type="PropSet">
		<PropertySet name="object_physical_character_stats_BaseAttackParameters" nameUID="0x8EA2B0B2" schema="object-physical-character-stats-BaseAttackParameters">
			<!-- Schema Properties -->
			<Property name="MaxDistanceToChooseCloseAttack" type="Float32">2.75</Property>
			<Property name="ExitDistanceForCloseAttack" type="Float32">3.75</Property>
			<Property name="MaxDistanceToChooseMidAttack" type="Float32">5</Property>
			<Property name="ExitDistanceForMidAttack" type="Float32">7</Property>
			<Property name="MaxDistanceToUseCloseAttack" type="Float32">1.75</Property>
			<Property name="MaxDistanceToUseMidAttack" type="Float32">3</Property>
			<Property name="ChanceToUseMidAttack" type="Int32">20</Property>
			<Property name="MinRunningAttackDistance" type="Float32">6</Property>
			<Property name="MaxRunningAttackDistance" type="Float32">9</Property>
			<Property name="RunningAttackExitDistance" type="Float32">12</Property>
			<Property name="MaxOpportunisticMeleeAttackDistanceVSPlayer" type="Float32">2</Property>
			<Property name="MaxOpportunisticMeleeAttackDistanceVSAI" type="Float32">2</Property>
			<Property name="MaxOpportunisticMeleeExitDistance" type="Float32">1</Property>
			<Property name="MaxOpportunityMeleeAttackDistanceVSPlayer" type="Float32">1.5</Property>
			<Property name="MaxOpportunityMeleeAttackDistanceVSAI" type="Float32">1.5</Property>
			<Property name="MaxOpportunityMeleeExitDistance" type="Float32">1</Property>
			<Property name="MinTimeBeforeOpportunityMeleeAttack" type="Float32">0.25</Property>
			<Property name="MaxTimeBeforeOpportunityMeleeAttack" type="Float32">0.5</Property>
			<Property name="MinForOpportunityMeleeAttackTimeout" type="Float32">2</Property>
			<Property name="MaxForOpportunityMeleeAttackTimeout" type="Float32">3</Property>
			<Property name="MaxOpportunityRangedAttackDistanceVSPlayer" type="Float32">5</Property>
			<Property name="MaxOpportunityRangedAttackDistanceVSAI" type="Float32">5</Property>
			<Property name="MaxOpportunityRangedExitDistance" type="Float32">1</Property>
			<Property name="MinTimeBeforeOpportunityRangedAttack" type="Float32">0.25</Property>
			<Property name="MaxTimeBeforeOpportunityRangedAttack" type="Float32">0.5</Property>
			<Property name="MinTimeBeforeNextOpportunityRangedAttack" type="Float32">2.5</Property>
			<Property name="MaxTimeBeforeNextOpportunityRangedAttack" type="Float32">3</Property>
			<Property name="InitialAttackTimeMinMeleeVSHumanAsEnemy" type="Float32">0</Property>
			<Property name="InitialAttackTimeMaxMeleeVSHumanAsEnemy" type="Float32">0.4</Property>
			<Property name="AttackTimeMinMeleeVSHumanAsEnemy" type="Float32">0.7</Property>
			<Property name="AttackTimeMaxMeleeVSHumanAsEnemy" type="Float32">1.2</Property>
			<Property name="AttackTimeMinMeleeVSHumanAsEnemyMobBattle" type="Float32">0.25</Property>
			<Property name="AttackTimeMaxMeleeVSHumanAsEnemyMobBattle" type="Float32">1</Property>
			<Property name="AttackTimeMinMeleeDownedVSHumanAsEnemy" type="Float32">3</Property>
			<Property name="AttackTimeMaxMeleeDownedVSHumanAsEnemy" type="Float32">5</Property>
			<Property name="InitialAttackTimeMinRangedVSHumanAsEnemy" type="Float32">0.25</Property>
			<Property name="InitialAttackTimeMaxRangedVSHumanAsEnemy" type="Float32">1.5</Property>
			<Property name="AttackTimeMinRangedVSHumanAsEnemy" type="Float32">1</Property>
			<Property name="AttackTimeMaxRangedVSHumanAsEnemy" type="Float32">1.5</Property>
			<Property name="AttackTimeMinRangedDownedVSHumanAsEnemy" type="Float32">3.5</Property>
			<Property name="AttackTimeMaxRangedDownedVSHumanAsEnemy" type="Float32">4</Property>
			<Property name="InitialAttackTimeMinRangedInCoverVSHumanAsEnemy" type="Float32">0.25</Property>
			<Property name="InitialAttackTimeMaxRangedInCoverVSHumanAsEnemy" type="Float32">1.5</Property>
			<Property name="AttackTimeMinRangedInCoverVSHumanAsEnemy" type="Float32">1</Property>
			<Property name="AttackTimeMaxRangedInCoverVSHumanAsEnemy" type="Float32">1.5</Property>
			<Property name="AttackTimeMinRangedInCoverDownedVSHumanAsEnemy" type="Float32">3.5</Property>
			<Property name="AttackTimeMaxRangedInCoverDownedVSHumanAsEnemy" type="Float32">4</Property>
			<Property name="InitialAttackTimeMinDirectFollowersVSHumanAsEnemy" type="Float32">1</Property>
			<Property name="InitialAttackTimeMaxDirectFollowersVSHumanAsEnemy" type="Float32">3</Property>
			<Property name="AttackTimeMinDirectFollowersVSHumanAsEnemy" type="Float32">2.5</Property>
			<Property name="AttackTimeMaxDirectFollowersVSHumanAsEnemy" type="Float32">8.5</Property>
			<Property name="AttackTimeMinDirectFollowersDownedVSHumanAsEnemy" type="Float32">1.5</Property>
			<Property name="AttackTimeMaxDirectFollowersDownedVSHumanAsEnemy" type="Float32">4</Property>
			<Property name="InitialAttackTimeMinMeleeVSAIAsEnemy" type="Float32">1</Property>
			<Property name="InitialAttackTimeMaxMeleeVSAIAsEnemy" type="Float32">4</Property>
			<Property name="AttackTimeMinMeleeVSAIAsEnemy" type="Float32">0.5</Property>
			<Property name="AttackTimeMaxMeleeVSAIAsEnemy" type="Float32">3</Property>
			<Property name="AttackTimeMinMeleeDownedVSAIAsEnemy" type="Float32">8</Property>
			<Property name="AttackTimeMaxMeleeDownedVSAIAsEnemy" type="Float32">12</Property>
			<Property name="InitialAttackTimeMinRangedVSAIAsEnemy" type="Float32">0.5</Property>
			<Property name="InitialAttackTimeMaxRangedVSAIAsEnemy" type="Float32">5.5</Property>
			<Property name="AttackTimeMinRangedVSAIAsEnemy" type="Float32">0.5</Property>
			<Property name="AttackTimeMaxRangedVSAIAsEnemy" type="Float32">6</Property>
			<Property name="AttackTimeMinRangedDownedVSAIAsEnemy" type="Float32">2</Property>
			<Property name="AttackTimeMaxRangedDownedVSAIAsEnemy" type="Float32">4</Property>
			<Property name="InitialAttackTimeMinRangedInCoverVSAIAsEnemy" type="Float32">0.25</Property>
			<Property name="InitialAttackTimeMaxRangedInCoverVSAIAsEnemy" type="Float32">1.5</Property>
			<Property name="AttackTimeMinRangedInCoverVSAIAsEnemy" type="Float32">3</Property>
			<Property name="AttackTimeMaxRangedInCoverVSAIAsEnemy" type="Float32">6</Property>
			<Property name="AttackTimeMinRangedInCoverDownedVSAIAsEnemy" type="Float32">1</Property>
			<Property name="AttackTimeMaxRangedInCoverDownedVSAIAsEnemy" type="Float32">4</Property>
			<Property name="InitialAttackTimeMinDirectFollowersVSAIAsEnemy" type="Float32">0.25</Property>
			<Property name="InitialAttackTimeMaxDirectFollowersVSAIAsEnemy" type="Float32">1.5</Property>
			<Property name="AttackTimeMinDirectFollowersVSAIAsEnemy" type="Float32">3</Property>
			<Property name="AttackTimeMaxDirectFollowersVSAIAsEnemy" type="Float32">4</Property>
			<Property name="AttackTimeMinDirectFollowersDownedVSAIAsEnemy" type="Float32">2</Property>
			<Property name="AttackTimeMaxDirectFollowersDownedVSAIAsEnemy" type="Float32">4</Property>
			<Property name="InitialAttackTimeMinMeleeVSAIAsAlly" type="Float32">0.1</Property>
			<Property name="InitialAttackTimeMaxMeleeVSAIAsAlly" type="Float32">0.4</Property>
			<Property name="AttackTimeMinMeleeVSAIAsAlly" type="Float32">0.5</Property>
			<Property name="AttackTimeMaxMeleeVSAIAsAlly" type="Float32">1</Property>
			<Property name="AttackTimeMinMeleeDownedVSAIAsAlly" type="Float32">2</Property>
			<Property name="AttackTimeMaxMeleeDownedVSAIAsAlly" type="Float32">3</Property>
			<Property name="InitialAttackTimeMinRangedVSAIAsAlly" type="Float32">2</Property>
			<Property name="InitialAttackTimeMaxRangedVSAIAsAlly" type="Float32">5</Property>
			<Property name="AttackTimeMinRangedVSAIAsAlly" type="Float32">1.5</Property>
			<Property name="AttackTimeMaxRangedVSAIAsAlly" type="Float32">2.5</Property>
			<Property name="AttackTimeMinRangedDownedVSAIAsAlly" type="Float32">1</Property>
			<Property name="AttackTimeMaxRangedDownedVSAIAsAlly" type="Float32">3</Property>
			<Property name="InitialAttackTimeMinRangedInCoverVSAIAsAlly" type="Float32">2.5</Property>
			<Property name="InitialAttackTimeMaxRangedInCoverVSAIAsAlly" type="Float32">5</Property>
			<Property name="AttackTimeMinRangedInCoverVSAIAsAlly" type="Float32">2.5</Property>
			<Property name="AttackTimeMaxRangedInCoverVSAIAsAlly" type="Float32">8</Property>
			<Property name="AttackTimeMinRangedInCoverDownedVSAIAsAlly" type="Float32">2</Property>
			<Property name="AttackTimeMaxRangedInCoverDownedVSAIAsAlly" type="Float32">8</Property>
			<Property name="InitialAttackTimeMinDirectFollowersVSAIAsAlly" type="Float32">2.5</Property>
			<Property name="InitialAttackTimeMaxDirectFollowersVSAIAsAlly" type="Float32">4</Property>
			<Property name="AttackTimeMinDirectFollowersVSAIAsAlly" type="Float32">2.5</Property>
			<Property name="AttackTimeMaxDirectFollowersVSAIAsAlly" type="Float32">4</Property>
			<Property name="AttackTimeMinDirectFollowersDownedVSAIAsAlly" type="Float32">2</Property>
			<Property name="AttackTimeMaxDirectFollowersDownedVSAIAsAlly" type="Float32">4</Property>
		</PropertySet>
	</Property>
	<Property name="InterruptChance" type="Int32">0</Property>
	<Property name="component_Health" type="PropSet">
		<PropertySet name="component_Health" nameUID="0xA9EB4546" schema="default-component-Health">
			<!-- Schema Properties -->
			<Property name="maxUpgradedHealth" type="Int32">400</Property>
			<Property name="maxHealth" type="Int32">145</Property>
			<Property name="regenerativeHealthRate" type="Float32">-1</Property>
			<Property name="InvulnerableCharacter" type="Boolean">false</Property>
			<Property name="healthProjectileDamageMultiplier" type="Float32">0.72</Property>
		</PropertySet>
	</Property>
	<Property name="component_CharacterProperties" type="PropSet">
		<PropertySet name="component_CharacterProperties" nameUID="0xBF516446" schema="default-component-CharacterProperties">
			<!-- Schema Properties -->
			<Property name="simObjectCharacterType" type="Symbol" symUID="0xD2BB8C2">eCHARACTER_TYPE_THUG</Property>
			<Property name="simObjectCharacterIsFemale" type="Boolean">false</Property>
			<Property name="simObjectCharacterFightingClass" type="Symbol" symUID="0x8CF3134E">eFIGHTING_CLASS_TUTORIAL</Property>
			<Property name="Stamina" type="Int32">100</Property>
			<Property name="PoiCooldownTimeMin" type="Float32">0</Property>
			<Property name="PoiCooldownTimeMax" type="Float32">0</Property>
			<Property name="FactionClass" type="Symbol" symUID="0x2FDA7843">TRIAD_WINSTON</Property>
			<Property name="Gender" type="Symbol" symUID="0x166A8B5C">Male</Property>
			<Property name="IsTired" type="Boolean">false</Property>
			<!-- Schema Parent: component_SimObjectProperties -->
		</PropertySet>
	</Property>
	<Property name="component_SimObjectProperties" type="PropSet">
		<PropertySet name="component_CharacterProperties" nameUID="0xBF516446" schema="default-component-CharacterProperties">
			<!-- Schema Properties -->
			<Property name="simObjectType" type="Symbol" symUID="0xA94623B7">eSIM_OBJ_TYPE_CHARACTER</Property>
			<Property name="subTargetingProfile" type="Symbol" symUID="0xD447D38">Targeting-SubTargetingProfiles-Character</Property>
		</PropertySet>
	</Property>
	<Property name="Description" type="String">Conroy Tutorial</Property>
</PropertySetResource>
