<PropertySet name="TrueCrowd-Characters_New-AM_H_068" nameUID="0x34E1F498" schema="TrueCrowd-Characters_New-AM_H_068">
    <Property name="GlassesOffset" type="PropSet">
        <PropertySet>
            <Property name="Rotation" type="Vector3" x="1.47795" y="1.47795" z="0"/>
            <Property name="Translation" type="Vector3" x="0" y="0" z="0.0142529"/>
        </PropertySet>
    </Property>
    <Property name="HatOffset" type="PropSet">
        <PropertySet>
            <Property name="Translation" type="Vector3" x="0" y="0" z="-0.00699951"/>
        </PropertySet>
    </Property>
    <Property name="HelmetOffset" type="PropSet">
        <PropertySet>
            <Property name="Rotation" type="Vector3" x="-2.87272" y="-2.87272" z="0"/>
            <Property name="Translation" type="Vector3" x="0" y="0" z="-0.020426"/>
        </PropertySet>
    </Property>
</PropertySet>
