<Item Hash="0xA7AE1EF9" Name="Vehicles-AI_CheerProperties">
	<0x13DCD59E_FLOAT>0.500000</0x13DCD59E_FLOAT>
	<0x15985F81_FLOAT>1300.000000</0x15985F81_FLOAT>
	<0x16E86CBE_FLOAT>-5.000000</0x16E86CBE_FLOAT>
	<0x1729457B_FLOAT>2500.000000</0x1729457B_FLOAT>
	<0x17C59224_FLOAT>0.500000</0x17C59224_FLOAT>
	<0x18188C7F_FLOAT>0.000000</0x18188C7F_FLOAT>
	<0x1901B266_FLOAT>100.000000</0x1901B266_FLOAT>
	<0x19B18E6E_FLOAT>0.000000</0x19B18E6E_FLOAT>
	<0x2AF75BF6_FLOAT>1.500000</0x2AF75BF6_FLOAT>
	<0x2C51A9B1_FLOAT>3.000000</0x2C51A9B1_FLOAT>
	<0x2CCDA8FC_FLOAT>-0.500000</0x2CCDA8FC_FLOAT>
	<0x2D481EF3_FLOAT>0.200000</0x2D481EF3_FLOAT>
	<0x2DF35F4_FLOAT>50.000000</0x2DF35F4_FLOAT>
	<0x2E00EC7E_FLOAT>5300.000000</0x2E00EC7E_FLOAT>
	<0x398C1359_FLOAT>0.445000</0x398C1359_FLOAT>
	<0x39B932E1_FLOAT>4.000000</0x39B932E1_FLOAT>
	<0x3D084A8B_FLOAT>5.000000</0x3D084A8B_FLOAT>
	<0x3D149EC8_FLOAT>50000.000000</0x3D149EC8_FLOAT>
	<0x3DDA103C_FLOAT>1.000000</0x3DDA103C_FLOAT>
	<0x40B5ACA9_FLOAT>60.000000</0x40B5ACA9_FLOAT>
	<0x426D413F_FLOAT>6.000000</0x426D413F_FLOAT>
	<0x4508DCB6_FLOAT>0.330000</0x4508DCB6_FLOAT>
	<0x47F95A96_FLOAT>0.050000</0x47F95A96_FLOAT>
	<0x49E63B0D_FLOAT>8500.000000</0x49E63B0D_FLOAT>
	<0x4BC85E45_FLOAT>0.000000</0x4BC85E45_FLOAT>
	<0x4DB3B896_FLOAT>8500.000000</0x4DB3B896_FLOAT>
	<0x4DDD3B93_FLOAT>0.800000</0x4DDD3B93_FLOAT>
	<0x52CC9D4F_FLOAT>0.000000</0x52CC9D4F_FLOAT>
	<0x530E3F31_FLOAT>3.500000</0x530E3F31_FLOAT>
	<0x54FA4C47_FLOAT>2.000000</0x54FA4C47_FLOAT>
	<0x55661811_FLOAT>0.000000</0x55661811_FLOAT>
	<0x569CC509_FLOAT>20.000000</0x569CC509_FLOAT>
	<0x5710A098_FLOAT>1.300000</0x5710A098_FLOAT>
	<0x5921A650_FLOAT>8500.000000</0x5921A650_FLOAT>
	<0x5A226875_FLOAT>70.000000</0x5A226875_FLOAT>
	<0x5E3F8F83_FLOAT>0.800000</0x5E3F8F83_FLOAT>
	<0x5EFD1C59_FLOAT>0.000000</0x5EFD1C59_FLOAT>
	<0x63011B9C_FLOAT>1.000000</0x63011B9C_FLOAT>
	<0x662E7F42_FLOAT>1.000000</0x662E7F42_FLOAT>
	<0x670767FA_FLOAT>250.000000</0x670767FA_FLOAT>
	<0x69641049_FLOAT>8.000000</0x69641049_FLOAT>
	<0x6E506C7B_FLOAT>3.000000</0x6E506C7B_FLOAT>
	<0x6E9BB9B8_FLOAT>1000.000000</0x6E9BB9B8_FLOAT>
	<0x6F734676_FLOAT>0.050000</0x6F734676_FLOAT>
	<0x70478875_FLOAT>4.000000</0x70478875_FLOAT>
	<0x71C3CE4D_FLOAT>1.150000</0x71C3CE4D_FLOAT>
	<0x77AD1BED_FLOAT>0.500000</0x77AD1BED_FLOAT>
	<0x7C2FD54_FLOAT>250.000000</0x7C2FD54_FLOAT>
	<0x7D04684_FLOAT>0.000000</0x7D04684_FLOAT>
	<0x7FB963E_FLOAT>4.300000</0x7FB963E_FLOAT>
	<0x807780E7_FLOAT>6.000000</0x807780E7_FLOAT>
	<0x80EC2094_FLOAT>1.150000</0x80EC2094_FLOAT>
	<0x8133CBDA_FLOAT>1.650000</0x8133CBDA_FLOAT>
	<0x82D4D8EA_FLOAT>-0.500000</0x82D4D8EA_FLOAT>
	<0x863910AF_FLOAT>56.000000</0x863910AF_FLOAT>
	<0x8788AEE5_FLOAT>0.800000</0x8788AEE5_FLOAT>
	<0x879012BE_FLOAT>130.000000</0x879012BE_FLOAT>
	<0x8D25BD30_FLOAT>0.000000</0x8D25BD30_FLOAT>
	<0x8E430AB8_FLOAT>1.500000</0x8E430AB8_FLOAT>
	<0x8EE86D9C_FLOAT>0.000000</0x8EE86D9C_FLOAT>
	<0x8FA5BA7B_FLOAT>235.000000</0x8FA5BA7B_FLOAT>
	<0x91787A75_FLOAT>0.010000</0x91787A75_FLOAT>
	<0x91A840A0_FLOAT>1.150000</0x91A840A0_FLOAT>
	<0x91EA60A_FLOAT>0.200000</0x91EA60A_FLOAT>
	<0x9275184C_FLOAT>3.500000</0x9275184C_FLOAT>
	<0x946F2ED3_FLOAT>35.000000</0x946F2ED3_FLOAT>
	<0x95DD4749_FLOAT>700.000000</0x95DD4749_FLOAT>
	<0xD1898598_VECTOR3>0.00, 0.00, 0.15</0xD1898598_VECTOR3>
	<0xF2F48DE0_VECTOR3>0.00, 0.00, 0.15</0xF2F48DE0_VECTOR3>
	<aerodynamics_frontalArea>4.000000</aerodynamics_frontalArea>
	<blownTire_FrictionMultiplier>0.250000</blownTire_FrictionMultiplier>
	<brakes_frontMinPedalInputToBlock>0.800000</brakes_frontMinPedalInputToBlock>
	<brakes_maxTorqueFront>1200.000000</brakes_maxTorqueFront>
	<brakes_minTimeToBlock>1.000000</brakes_minTimeToBlock>
	<brakes_rearMinPedalInputToBlock>0.800000</brakes_rearMinPedalInputToBlock>
	<burnout_FwdThrustFactor_HighSpeed>1.150000</burnout_FwdThrustFactor_HighSpeed>
	<burnout_SideThrustFactor_LowSpeed>1.150000</burnout_SideThrustFactor_LowSpeed>
	<burnout_SpinRearTireFrictionAtHighSpeed>0.400000</burnout_SpinRearTireFrictionAtHighSpeed>
	<burnout_TorqueFactor_LowSpeed>1.150000</burnout_TorqueFactor_LowSpeed>
	<burnout_UseNewMethod>0</burnout_UseNewMethod>
	<chassis_physicsProperties>CarChassis</chassis_physicsProperties>
	<collision_friction>0.100000</collision_friction>
	<damping_normalSpinDamping>3.000000</damping_normalSpinDamping>
	<disableDoorL02>0</disableDoorL02>
	<disableDoorL03>1</disableDoorL03>
	<disableDoorR02>0</disableDoorR02>
	<disableDoorR03>1</disableDoorR03>
	<disableTrunk>0</disableTrunk>
	<drivetrain_gearRatio1>6.000000</drivetrain_gearRatio1>
	<drivetrain_gearRatio2>4.000000</drivetrain_gearRatio2>
	<drivetrain_gearRatio3>2.800000</drivetrain_gearRatio3>
	<drivetrain_gearRatio4>1.900000</drivetrain_gearRatio4>
	<drivetrain_gearRatio5>1.600000</drivetrain_gearRatio5>
	<drivetrain_rearWheelTorqueRatio>0.000000</drivetrain_rearWheelTorqueRatio>
	<engine_maxRPM>6500.000000</engine_maxRPM>
	<engine_minRPM>500.000000</engine_minRPM>
	<engine_optRPM>5500.000000</engine_optRPM>
	<engine_resistanceMax>0.100000</engine_resistanceMax>
	<engine_resistanceMinSpeed>0.000000</engine_resistanceMinSpeed>
	<lodHeightFixupFront>0.019000</lodHeightFixupFront>
	<lodHeightFixupRear>0.019000</lodHeightFixupRear>
	<numWheels>4</numWheels>
	<other_chassisUnitInertiaPitch>1.700000</other_chassisUnitInertiaPitch>
	<other_chassisUnitInertiaRoll>1.000000</other_chassisUnitInertiaRoll>
	<other_cruiseControlPID_p>1.000000</other_cruiseControlPID_p>
	<other_frictionEqualizer>0.200000</other_frictionEqualizer>
	<other_normalClippingAngle>0.200000</other_normalClippingAngle>
	<other_torquePitchFactor>0.650000</other_torquePitchFactor>
	<other_torqueRollFactor>0.420000</other_torqueRollFactor>
	<other_torqueYawFactor>0.420000</other_torqueYawFactor>
	<other_verticalVelocityDampingDown>-200.000000</other_verticalVelocityDampingDown>
	<pad_BasePhysicsProperties>0</pad_BasePhysicsProperties>
	<pitchStability>0.000000</pitchStability>
	<rollStability>4.000000</rollStability>
	<steering_CenteringRate>100.000000</steering_CenteringRate>
	<steering_DeadZone>0.000000</steering_DeadZone>
	<steering_FrontWheelMultiplier>1.000000</steering_FrontWheelMultiplier>
	<steering_RearWheelMultiplier>0.000000</steering_RearWheelMultiplier>
	<steering_maxAngle>45.000000</steering_maxAngle>
	<superStop_Drag>12000.000000</superStop_Drag>
	<suspension_angle_front>0.000000</suspension_angle_front>
	<suspension_frontSpringRate>25.000000</suspension_frontSpringRate>
	<suspension_frontSpringRestingLength>0.878000</suspension_frontSpringRestingLength>
	<suspension_frontUpTravelLimit>0.100000</suspension_frontUpTravelLimit>
	<suspension_rearUpTravelLimit>0.100000</suspension_rearUpTravelLimit>
	<wheels_forceFeedbackMultiplier>1.000000</wheels_forceFeedbackMultiplier>
	<wheels_frictionRear>1.550000</wheels_frictionRear>
	<wheels_mass>15.000000</wheels_mass>
	<wheels_radius_front>0.360000</wheels_radius_front>
	<wheels_radius_rear>0.360000</wheels_radius_rear>
</Item>
