{
    "M_TNB_LIMOTHUG.M_TNB.900.A": {
        "DE": "Steigen Sie ein. Steigen Sie ein.",
        "EN": "Get in! Get in!",
        "FR": "Monte ! Monte !",
        "IT": "Dentro! Dentro!",
        "PO": "Wsiadaj! Wsiadaj!",
        "RU": "Садись! Садись!",
        "SP": "¡Sube! ¡Sube!"
    },
    "M_TNB_LIMOTHUG.M_TNB.901.A": {
        "DE": "Mäßigen Sie Ihren Ton, Shen. Ms. Jiang ist ein Red Pole. Und sie hat Ihnen gerade das Leben gerettet.",
        "EN": "Change your tone, Shen. Ms. Jiang is a Red Pole. And she just saved your life.",
        "FR": "Change de ton, Shen. Madame Jiang est Bâton rouge. Et elle vient de te sauver la vie.",
        "IT": "Bada a come parli, Shen. Ms. Jiang è un Palo Rosso. E ti ha appena salvato la vita.",
        "PO": "Nie tak ostro, Shen. Pani Jiang jest Czerwonym Kijem. I właśnie ocaliła ci życie.",
        "RU": "Смени тон, Шень. Миссис Цзян - красный шест. И она только что спасла тебе жизнь.",
        "SP": "Cambia el tono, Shen. La Sra. Jiang es una Red Pole. Y te acaba de salvar la vida."
    },
    "WEI.M_TNB.990.A": {
        "DE": "Was zur Hölle?",
        "EN": "What the hell?",
        "FR": "C'est quoi ça ?",
        "IT": "Ma che diavolo?",
        "PO": "Co do diabła?",
        "RU": "Что за черт?",
        "SP": "¿Qué diablos...?"
    },
    "WEI.M_TNB.991.A": {
        "DE": "Wer zum Teufel seid ihr Typen?",
        "EN": "Who the fuck are you guys?",
        "FR": "Vous êtes qui, putain ?",
        "IT": "E voi chi cazzo siete?",
        "PO": "Kim wy, kurwa, jesteście?",
        "RU": "Ребята, вы кто на хер такие?",
        "SP": "¿Quién coño sois vosotros?"
    },
    "WEI.M_TNB.992.A": {
        "DE": "Ms. Jiang? Broken Nose Jiang? Entschuldigen Sie, Madame Red Pole.",
        "EN": "Ms. Jiang? Broken Nose Jiang? My apologies, madam Red Pole.",
        "FR": "Madame Jiang ? Nez-Cassé Jiang ? Je suis désolé, madame Bâton rouge...",
        "IT": "Ms. Jiang? Jiang Nasorotto? Mi dispiace, Palo Rosso.",
        "PO": "Pani Jiang? Krzywonosa Jiang? Najmocniej przepraszam.",
        "RU": "Миссис Цзян? Кривоносая Цзян? Примите мои извинения, госпожа красный шест.",
        "SP": "¿Sra. Jiang? ¿Nariz Rota Jiang? Mis disculpas, señora Red Pole."
    }
}