<PropertySet name="object-physical-vehicle-Etalon_Race02" nameUID="0x814F53DD" schema="object-physical-vehicle-Etalon_Race02">
    <Parent>object-physical-vehicle-etalon01</Parent>
    <Property name="Description" type="String">2Dr- Etalon_Race2</Property>
    <Property name="VehicleLook" type="List">
        <Property type="String">WhitePaint</Property>
    </Property>
    <Property name="VehicleLookGlass" type="List">
        <Property type="String">GlassBlack02</Property>
    </Property>
    <Property name="component_BaseAnimation" type="PropSet"/>
    <Property name="component_CharacterAnimation" type="PropSet"/>
    <Property name="component_StreamedResource" type="PropSet"/>
    <Property name="component_VehicleEffects" type="PropSet"/>
</PropertySet>
