<PropertySet name="object-physical-weapon-melee-TelescopingBaton001" nameUID="0x2E96AFAC" schema="object-physical-weapon-melee-TelescopingBaton001">
    <Parent>object-physical-weapon-melee-baton</Parent>
    <Property name="ActFileName" type="String">Data\Global\Act\TelescopingBaton001.act</Property>
    <Property name="Description" type="String">$HUD_WEAPON_NIGHTSTICK</Property>
    <Property name="IsTelescopingBaton" type="Boolean">True</Property>
    <Property name="Stowable" type="Boolean">True</Property>
    <Property name="component_BaseAnimation" type="PropSet"/>
    <Property name="component_CharacterAnimation" type="PropSet"/>
    <Property name="component_InventoryItem" type="PropSet"/>
    <Property name="component_StreamedResource" type="PropSet"/>
</PropertySet>
