
<?xml version="1.0"?>

<scenesettingsgroup>	
	<scenesettings name="Settings_WTHK_1_Intro_Nis">		
		<teleportlocationmarker name = "WTHKMission-Restore_2_Movement_Tutorial"></teleportlocationmarker>
		<forceweather type="heavyrain" wetness="1.0" locked="true"></forceweather>		
	</scenesettings>	
	<scenesettings name="Settings_WTHK_1_Arrested_Nis">		
		<teleportlocationmarker name = "Locations-GU_spawn"></teleportlocationmarker>
	</scenesettings>
	<scenesettings name="Settings_WTHK_1_Naz_Arrested_Nis">		
		<teleportlocationmarker name = "WTHKMission-Restore_5_Final_Chase"></teleportlocationmarker>
	</scenesettings>		
</scenesettingsgroup>	